{
  "project_info": {
    "project_number": "511157486237",
    "firebase_url": "https://darkoob-d4a22.firebaseio.com",
    "project_id": "darkoob-d4a22",
    "storage_bucket": "darkoob-d4a22.appspot.com"
  },
  "client": [
    {
      "client_info": {
        "mobilesdk_app_id": "1:511157486237:android:51432dd5067b61e0",
        "android_client_info": {
          "package_name": "com.yekaan.darkoob"
        }
      },
      "oauth_client": [
        {
          "client_id": "511157486237-so79hj2aip038dh7kvt264231h37bqon.apps.googleusercontent.com",
          "client_type": 3
        }
      ],
      "api_key": [
        {
          "current_key": "AIzaSyDRvvAQho-cRM8iw5230e00SWwrul2ZBMs"
        }
      ],
      "services": {
        "appinvite_service": {
          "other_platform_oauth_client": [
            {
              "client_id": "511157486237-so79hj2aip038dh7kvt264231h37bqon.apps.googleusercontent.com",
              "client_type": 3
            },
            {
              "client_id": "511157486237-6kh7jrmmh1c0vt30kk0njtjoujl2rkhd.apps.googleusercontent.com",
              "client_type": 2,
              "ios_info": {
                "bundle_id": "darkoob"
              }
            }
          ]
        }
      }
    },
    {
      "client_info": {
        "mobilesdk_app_id": "1:511157486237:android:798d93bc4cf3d725",
        "android_client_info": {
          "package_name": "com.yekaan.darkoob.cloud"
        }
      },
      "oauth_client": [
        {
          "client_id": "511157486237-so79hj2aip038dh7kvt264231h37bqon.apps.googleusercontent.com",
          "client_type": 3
        }
      ],
      "api_key": [
        {
          "current_key": "AIzaSyDRvvAQho-cRM8iw5230e00SWwrul2ZBMs"
        }
      ],
      "services": {
        "appinvite_service": {
          "other_platform_oauth_client": [
            {
              "client_id": "511157486237-so79hj2aip038dh7kvt264231h37bqon.apps.googleusercontent.com",
              "client_type": 3
            },
            {
              "client_id": "511157486237-6kh7jrmmh1c0vt30kk0njtjoujl2rkhd.apps.googleusercontent.com",
              "client_type": 2,
              "ios_info": {
                "bundle_id": "darkoob"
              }
            }
          ]
        }
      }
    },
    {
      "client_info": {
        "mobilesdk_app_id": "1:511157486237:android:b6de882244b442b3",
        "android_client_info": {
          "package_name": "com.yekaan.darkoob.dev"
        }
      },
      "oauth_client": [
        {
          "client_id": "511157486237-so79hj2aip038dh7kvt264231h37bqon.apps.googleusercontent.com",
          "client_type": 3
        }
      ],
      "api_key": [
        {
          "current_key": "AIzaSyDRvvAQho-cRM8iw5230e00SWwrul2ZBMs"
        }
      ],
      "services": {
        "appinvite_service": {
          "other_platform_oauth_client": [
            {
              "client_id": "511157486237-so79hj2aip038dh7kvt264231h37bqon.apps.googleusercontent.com",
              "client_type": 3
            },
            {
              "client_id": "511157486237-6kh7jrmmh1c0vt30kk0njtjoujl2rkhd.apps.googleusercontent.com",
              "client_type": 2,
              "ios_info": {
                "bundle_id": "darkoob"
              }
            }
          ]
        }
      }
    },
    {
      "client_info": {
        "mobilesdk_app_id": "1:511157486237:android:6cbc708aa3cbdc433eca74",
        "android_client_info": {
          "package_name": "com.yekaan.darkoob.notiff.ir"
        }
      },
      "oauth_client": [
        {
          "client_id": "511157486237-so79hj2aip038dh7kvt264231h37bqon.apps.googleusercontent.com",
          "client_type": 3
        }
      ],
      "api_key": [
        {
          "current_key": "AIzaSyDRvvAQho-cRM8iw5230e00SWwrul2ZBMs"
        }
      ],
      "services": {
        "appinvite_service": {
          "other_platform_oauth_client": [
            {
              "client_id": "511157486237-so79hj2aip038dh7kvt264231h37bqon.apps.googleusercontent.com",
              "client_type": 3
            },
            {
              "client_id": "511157486237-6kh7jrmmh1c0vt30kk0njtjoujl2rkhd.apps.googleusercontent.com",
              "client_type": 2,
              "ios_info": {
                "bundle_id": "darkoob"
              }
            }
          ]
        }
      }
    },
    {
      "client_info": {
        "mobilesdk_app_id": "1:511157486237:android:464f03c73697c8573eca74",
        "android_client_info": {
          "package_name": "ir.yekaan.darkoobnext"
        }
      },
      "oauth_client": [
        {
          "client_id": "511157486237-so79hj2aip038dh7kvt264231h37bqon.apps.googleusercontent.com",
          "client_type": 3
        }
      ],
      "api_key": [
        {
          "current_key": "AIzaSyDRvvAQho-cRM8iw5230e00SWwrul2ZBMs"
        }
      ],
      "services": {
        "appinvite_service": {
          "other_platform_oauth_client": [
            {
              "client_id": "511157486237-so79hj2aip038dh7kvt264231h37bqon.apps.googleusercontent.com",
              "client_type": 3
            },
            {
              "client_id": "511157486237-6kh7jrmmh1c0vt30kk0njtjoujl2rkhd.apps.googleusercontent.com",
              "client_type": 2,
              "ios_info": {
                "bundle_id": "darkoob"
              }
            }
          ]
        }
      }
    },
    {
      "client_info": {
        "mobilesdk_app_id": "1:511157486237:android:0f10886396eca1093eca74",
        "android_client_info": {
          "package_name": "ir.yekaan.darkoobnext.isfahan.ir"
        }
      },
      "oauth_client": [
        {
          "client_id": "511157486237-so79hj2aip038dh7kvt264231h37bqon.apps.googleusercontent.com",
          "client_type": 3
        }
      ],
      "api_key": [
        {
          "current_key": "AIzaSyDRvvAQho-cRM8iw5230e00SWwrul2ZBMs"
        }
      ],
      "services": {
        "appinvite_service": {
          "other_platform_oauth_client": [
            {
              "client_id": "511157486237-so79hj2aip038dh7kvt264231h37bqon.apps.googleusercontent.com",
              "client_type": 3
            },
            {
              "client_id": "511157486237-6kh7jrmmh1c0vt30kk0njtjoujl2rkhd.apps.googleusercontent.com",
              "client_type": 2,
              "ios_info": {
                "bundle_id": "darkoob"
              }
            }
          ]
        }
      }
    },
    {
      "client_info": {
        "mobilesdk_app_id": "1:511157486237:android:bb1a92f765efd5443eca74",
        "android_client_info": {
          "package_name": "ir.yekaan.darkoobnext.rasa"
        }
      },
      "oauth_client": [
        {
          "client_id": "511157486237-so79hj2aip038dh7kvt264231h37bqon.apps.googleusercontent.com",
          "client_type": 3
        }
      ],
      "api_key": [
        {
          "current_key": "AIzaSyDRvvAQho-cRM8iw5230e00SWwrul2ZBMs"
        }
      ],
      "services": {
        "appinvite_service": {
          "other_platform_oauth_client": [
            {
              "client_id": "511157486237-so79hj2aip038dh7kvt264231h37bqon.apps.googleusercontent.com",
              "client_type": 3
            },
            {
              "client_id": "511157486237-6kh7jrmmh1c0vt30kk0njtjoujl2rkhd.apps.googleusercontent.com",
              "client_type": 2,
              "ios_info": {
                "bundle_id": "darkoob"
              }
            }
          ]
        }
      }
    },
    {
      "client_info": {
        "mobilesdk_app_id": "1:511157486237:android:76a27d9d1b05849d3eca74",
        "android_client_info": {
          "package_name": "ir.yekaan.darkoobnext.urbantc.ir"
        }
      },
      "oauth_client": [
        {
          "client_id": "511157486237-so79hj2aip038dh7kvt264231h37bqon.apps.googleusercontent.com",
          "client_type": 3
        }
      ],
      "api_key": [
        {
          "current_key": "AIzaSyDRvvAQho-cRM8iw5230e00SWwrul2ZBMs"
        }
      ],
      "services": {
        "appinvite_service": {
          "other_platform_oauth_client": [
            {
              "client_id": "511157486237-so79hj2aip038dh7kvt264231h37bqon.apps.googleusercontent.com",
              "client_type": 3
            },
            {
              "client_id": "511157486237-6kh7jrmmh1c0vt30kk0njtjoujl2rkhd.apps.googleusercontent.com",
              "client_type": 2,
              "ios_info": {
                "bundle_id": "darkoob"
              }
            }
          ]
        }
      }
    }
  ],
  "configuration_version": "1"
}